QAWECHAT/__init__.py
quantaxis_wechat-1.0.dist-info/METADATA
quantaxis_wechat-1.0.dist-info/WHEEL
quantaxis_wechat-1.0.dist-info/top_level.txt
quantaxis_wechat-1.0.dist-info/zip-safe
quantaxis_wechat-1.0.dist-info/RECORD
