Metadata-Version: 2.1
Name: quantaxis-wechat
Version: 1.0
Summary: QUANTAXIS WECHAT: QUANTAXIS WECHAT CLIENT
Home-page: https://github.com/yutiansut/QAWECHAT
Author: yutiansut
Author-email: yutiansut@qq.com
License: MIT
Keywords: quantaxis,quant,finance,Backtest,Framework
Platform: UNKNOWN
Classifier: License :: OSI Approved :: MIT License
Classifier: Programming Language :: Python
Classifier: Intended Audience :: Developers
Classifier: Operating System :: OS Independent
Requires-Dist: wechatpy
Requires-Dist: flask
Requires-Dist: quantaxis (>=1.1.10.dev2)
